kappa/__init__.py
kappa/awsclient.py
kappa/context.py
kappa/event_source.py
kappa/function.py
kappa/log.py
kappa/policy.py
kappa/restapi.py
kappa/role.py
kappa/scripts/__init__.py
kappa/scripts/cli.py
kappa-0.5.1.dist-info/DESCRIPTION.rst
kappa-0.5.1.dist-info/METADATA
kappa-0.5.1.dist-info/RECORD
kappa-0.5.1.dist-info/WHEEL
kappa-0.5.1.dist-info/entry_points.txt
kappa-0.5.1.dist-info/metadata.json
kappa-0.5.1.dist-info/top_level.txt
kappa-0.5.1.dist-info/zip-safe
