Metadata-Version: 2.0
Name: kappa
Version: 0.5.1
Summary: A CLI tool for AWS Lambda developers
Home-page: https://github.com/garnaat/kappa
Author: Mitch Garnaat
Author-email: mitch@garnaat.com
License: Apache License 2.0
Platform: UNKNOWN
Classifier: Development Status :: 3 - Alpha
Classifier: Intended Audience :: Developers
Classifier: Intended Audience :: System Administrators
Classifier: Natural Language :: English
Classifier: License :: OSI Approved :: Apache Software License
Classifier: Programming Language :: Python
Classifier: Programming Language :: Python :: 2.7
Classifier: Programming Language :: Python :: 3
Classifier: Programming Language :: Python :: 3.3
Classifier: Programming Language :: Python :: 3.4
Classifier: Programming Language :: Python :: 3.5
Requires-Dist: PyYAML (>=3.11)
Requires-Dist: boto3 (>=1.2.3)
Requires-Dist: click (>=5.1)
Requires-Dist: placebo (>=0.8.1)
